{
  "container": "postgres",
  "version": "18-alpine",
  "tag": "18-alpine-timeseries",
  "flavor": "timeseries",
  "dockerfile": "/tmp/Dockerfile.postgres.tO8T2I",
  "platform": "linux/amd64",
  "runtime": "GitHub Actions (registry cache)",
  "image_id": "unknown",
  "build_digest": "0de1d439e24c",
  "base_image_ref": "postgres:18-alpine",
  "base_image_digest": "unresolved",
  "built_at": "2026-02-02T18:51:36+00:00",
  "github_actions": true,
  "images": {
    "dockerhub": "docker.io/oorabona/postgres:18-alpine-timeseries",
    "ghcr": "ghcr.io/oorabona/postgres:18-alpine-timeseries"
  },
  "build_args": {}
}
